app/__init__.py
app/main.py
crdb_mcp_server/__init__.py
crdb_mcp_server/__main__.py
crdb_mcp_server/cli.py
crdb_mcp_server/config.py
crdb_mcp_server/logging_config.py
crdb_mcp_server/schema_init.py
crdb_mcp_server/server.py
crdb_mcp_server-0.1.0.dist-info/licenses/LICENSE
crdb_mcp_server-0.1.0.dist-info/METADATA
crdb_mcp_server-0.1.0.dist-info/WHEEL
crdb_mcp_server-0.1.0.dist-info/entry_points.txt
crdb_mcp_server-0.1.0.dist-info/top_level.txt
crdb_mcp_server-0.1.0.dist-info/RECORD
