Metadata-Version: 2.4
Name: crdb-mcp-server
Version: 0.1.0
Summary: Model Context Protocol server with CockroachDB
Author-email: Virag Tripathi <virag.tripathi@gmail.com>
License-Expression: MIT
Classifier: Development Status :: 4 - Beta
Classifier: Intended Audience :: Developers
Classifier: Topic :: Software Development :: Quality Assurance
Classifier: Programming Language :: Python :: 3
Classifier: Programming Language :: Python :: 3.7
Classifier: Programming Language :: Python :: 3.8
Classifier: Programming Language :: Python :: 3.9
Classifier: Programming Language :: Python :: 3.10
Classifier: Operating System :: OS Independent
Requires-Python: >=3.9
License-File: LICENSE
Requires-Dist: sqlalchemy
Requires-Dist: sqlalchemy-cockroachdb
Requires-Dist: fastapi>=0.110.0
Requires-Dist: uvicorn[standard]>=0.29.0
Requires-Dist: psycopg2-binary>=2.9.9
Requires-Dist: python-dotenv>=1.0.1
Dynamic: license-file
